LICENSE.txt
MANIFEST.in
README.md
setup.py
bernmix/__init__.py
bernmix/bernmix.py
bernmix.egg-info/PKG-INFO
bernmix.egg-info/SOURCES.txt
bernmix.egg-info/dependency_links.txt
bernmix.egg-info/not-zip-safe
bernmix.egg-info/requires.txt
bernmix.egg-info/top_level.txt
bernmix/bernmix_control/__init__.py
bernmix/bernmix_control/bernmix_control.py
bernmix/bernmix_double/__init__.py
bernmix/bernmix_double/bernmix_correction.py
bernmix/bernmix_double/bernmix_double.py
bernmix/bernmix_fancy/__init__.py
bernmix/bernmix_fancy/bm_dynam.py
bernmix/bernmix_int/__init__.py
bernmix/bernmix_int/bernmix_fourier.c
bernmix/bernmix_int/bernmix_fourier.h
bernmix/bernmix_int/bernmix_int.c
bernmix/bernmix_int/bernmix_int.pyx