Metadata-Version: 2.1
Name: bernmix
Version: 1.11.45
Summary: Methods to compute PMF and CDF values of a weighted sum of i.ni.d. BRVs
Home-page: https://github.com/iganna/bernmix
Author: Anna Igolkina
Author-email: igolkinaanna11@gmail.com
License: MIT
Platform: UNKNOWN
Classifier: Development Status :: 3 - Alpha
Classifier: Intended Audience :: Science/Research
Classifier: License :: OSI Approved :: MIT License
Classifier: Operating System :: OS Independent
Classifier: Programming Language :: Python
License-File: LICENSE.txt
